[
    {
        "id": "9587eed9-f323-4004-8cb9-47cab17f061f",
        "difficulty": "F\u00e1cil",
        "result": "Derrota",
        "time_elapsed": "00:00:00"
    },
    {
        "id": "1315252f-bffa-4767-98f2-54f33a3a301d",
        "difficulty": "F\u00e1cil",
        "result": "Derrota",
        "time_elapsed": "00:00:00"
    },
    {
        "id": "9b241589-037c-4098-a339-10a16c5ce713",
        "difficulty": "F\u00e1cil",
        "result": "Derrota",
        "time_elapsed": "00:00:00"
    },
    {
        "id": "7c4aa832-b23f-4462-bfbd-de3b1b6edcc0",
        "difficulty": "F\u00e1cil",
        "result": "Derrota",
        "time_elapsed": "00:00:00"
    },
    {
        "id": "5e58603e-c972-4b6e-8c5f-f02a210906d7",
        "difficulty": "F\u00e1cil",
        "result": "Derrota",
        "time_elapsed": "00:00:00"
    },
    {
        "id": "bfb5af81-5d44-4975-aff6-aa7abae29f64",
        "difficulty": "F\u00e1cil",
        "result": "Derrota",
        "time_elapsed": "00:00:00"
    },
    {
        "id": "45f871b5-4b2a-46c2-bfec-7dca6a868bfc",
        "difficulty": "Intermedi\u00e1rio",
        "result": "Derrota",
        "time_elapsed": "00:00:00"
    },
    {
        "id": "672fadfe-7e13-40d2-8cac-cab7489a3aae",
        "difficulty": "F\u00e1cil",
        "result": "Derrota",
        "time_elapsed": "00:00:00"
    },
    {
        "id": "da7259d9-8b9f-45e9-8edc-6d145e8ede3e",
        "difficulty": "F\u00e1cil",
        "result": "Derrota",
        "time_elapsed": "00:00:01"
    }
]